Iverilog+GTKWave/alu8bit.v
module alu8bit(
    input  [7:0] A,
    input  [7:0] B,
    input  [2:0] s,       
    output reg[7:0] y,
    output reg carry
);

always @(*) begin
    carry = 0; 
    
    case (s)
        3'b000: {carry, y} = A + B;      
        3'b001: {carry, y} = A - B;      
        3'b010: y = A & B;               
        3'b011: y = A | B;               
        3'b100: y = A ^ B;               
        3'b101: y = ~A;                  
        3'b110: y = A << 1;              
        3'b111: y = A >> 1;              
        default: y= 8'b00000000;
    endcase
end
endmodule

//In Verilog, outputs that are assigned inside an always block must be declared as reg, not plain wire (the default).

Iverilog+GTKWave/alu8bittb.v
`timescale 1ns/1ps  

module alu8bittb;

reg [7:0]A,B;
reg [2:0] s;
wire carry;
wire [7:0]y;

alu8bit uut(
    .A(A),
    .B(B),
    .s(s),
    .carry(carry),
    .y(y)
    );


initial begin

$dumpfile("alu8bitout.vcd");
$dumpvars(0,alu8bittb);

$monitor("Time=%0t, A=%0d, B=%0d, s=%b, y=%0d, carry=%b", $time, A, B, s, y, carry);

A=8'd10 ; B=8'd10;
s = 3'b000;
#10;

s = 3'b000; #10;  
s = 3'b001; #10;  
s = 3'b010; #10; 
s = 3'b011; #10;  
s = 3'b100; #10;  
s = 3'b101; #10;  
s = 3'b110; #10;  
s = 3'b111; #10; 

end 
endmodule

Iverilog+GTKWave/alu8bitout.vcd
$date
	Fri Sep  5 16:37:27 2025
$end
$version
	Icarus Verilog
$end
$timescale
	1ps
$end
$scope module alu8bittb $end
$var wire 8 ! y [7:0] $end
$var wire 1 " carry $end
$var reg 8 # A [7:0] $end
$var reg 8 $ B [7:0] $end
$var reg 3 % s [2:0] $end
$scope module uut $end
$var wire 8 & A [7:0] $end
$var wire 8 ' B [7:0] $end
$var wire 3 ( s [2:0] $end
$var reg 1 " carry $end
$var reg 8 ) y [7:0] $end
$upscope $end
$upscope $end
$enddefinitions $end
$comment Show the parameter values. $end
$dumpall
$end
#0
$dumpvars
b10100 )
b0 (
b1010 '
b1010 &
b0 %
b1010 $
b1010 #
0"
b10100 !
$end
#20000
b0 !
b0 )
b1 %
b1 (
#30000
b1010 !
b1010 )
b10 %
b10 (
#40000
b11 %
b11 (
#50000
b0 !
b0 )
b100 %
b100 (
#60000
b11110101 !
b11110101 )
b101 %
b101 (
#70000
b10100 !
b10100 )
b110 %
b110 (
#80000
b101 !
b101 )
b111 %
b111 (
